{
    "valid": [
        {
            "epoch": 0,
            "Accuracy": 0.0,
            "loss": 3.7904573033723845
        },
        {
            "epoch": 1,
            "Accuracy": 0.0,
            "loss": 3.482087195968112
        },
        {
            "epoch": 2,
            "Accuracy": 0.000486412181452892,
            "loss": 3.2391578486549677
        },
        {
            "epoch": 3,
            "Accuracy": 0.0009093792957597547,
            "loss": 3.0085414286717995
        },
        {
            "epoch": 4,
            "Accuracy": 0.001607275034366078,
            "loss": 2.789599643669851
        },
        {
            "epoch": 5,
            "Accuracy": 0.0029607698001480384,
            "loss": 2.591567845241304
        },
        {
            "epoch": 6,
            "Accuracy": 0.005054457015967008,
            "loss": 2.435092775682958
        },
        {
            "epoch": 7,
            "Accuracy": 0.007211589298932008,
            "loss": 2.5038422755846637
        },
        {
            "epoch": 8,
            "Accuracy": 0.0132388706778048,
            "loss": 2.161577930389141
        },
        {
            "epoch": 9,
            "Accuracy": 0.019689119170984457,
            "loss": 2.0456095358838247
        },
        {
            "epoch": 10,
            "Accuracy": 0.02829649994712911,
            "loss": 1.9251962562213893
        },
        {
            "epoch": 11,
            "Accuracy": 0.03935708998625357,
            "loss": 1.8236870991522307
        },
        {
            "epoch": 12,
            "Accuracy": 0.054753092947023366,
            "loss": 1.7266935856964978
        },
        {
            "epoch": 13,
            "Accuracy": 0.06788622184625145,
            "loss": 1.650000694156177
        }
    ],
    "train": [
        {
            "epoch": 0,
            "Accuracy": 0.0,
            "loss": 3.56544125146873
        },
        {
            "epoch": 1,
            "Accuracy": 0.0,
            "loss": 2.917401361363813
        },
        {
            "epoch": 2,
            "Accuracy": 0.0,
            "loss": 2.7181917409538916
        },
        {
            "epoch": 3,
            "Accuracy": 0.0,
            "loss": 2.5362356622253164
        },
        {
            "epoch": 4,
            "Accuracy": 0.0,
            "loss": 2.3624721465078493
        },
        {
            "epoch": 5,
            "Accuracy": 0.0,
            "loss": 2.199476742359803
        },
        {
            "epoch": 6,
            "Accuracy": 0.0,
            "loss": 2.0598783108200167
        },
        {
            "epoch": 7,
            "Accuracy": 0.0,
            "loss": 1.9378477127109792
        },
        {
            "epoch": 8,
            "Accuracy": 2.612432566584375e-06,
            "loss": 1.8257670721800083
        },
        {
            "epoch": 9,
            "Accuracy": 1.04497302663375e-05,
            "loss": 1.720343232872314
        },
        {
            "epoch": 10,
            "Accuracy": 2.0899460532675e-05,
            "loss": 1.6221913185285444
        },
        {
            "epoch": 11,
            "Accuracy": 5.486108389827188e-05,
            "loss": 1.5302217817123165
        },
        {
            "epoch": 12,
            "Accuracy": 7.31481118643625e-05,
            "loss": 1.4491583473266072
        },
        {
            "epoch": 13,
            "Accuracy": 0.00013062162832921874,
            "loss": 1.3740503358360638
        }
    ]
}